tiny.py
Tiny_interpolator-3.3.dist-info/DESCRIPTION.rst
Tiny_interpolator-3.3.dist-info/METADATA
Tiny_interpolator-3.3.dist-info/RECORD
Tiny_interpolator-3.3.dist-info/WHEEL
Tiny_interpolator-3.3.dist-info/metadata.json
Tiny_interpolator-3.3.dist-info/top_level.txt
