Metadata-Version: 2.0
Name: Tiny-interpolator
Version: 3.3
Summary: Powerful fully working Batch type ($) Variable-String Interpolation implementation for python.
Home-page: http://cyberforums.net/index.php?/profile/66-dote/
Author: valid22 (Dote)
Author-email: hidden@Security.email
License: UNKNOWN
Keywords: Variable-String Interpolatior
Platform: UNKNOWN
